simple/__init__.py
simple/__main__.py
yoshi_simple_temp-0.0.2.dist-info/LICENSE
yoshi_simple_temp-0.0.2.dist-info/METADATA
yoshi_simple_temp-0.0.2.dist-info/WHEEL
yoshi_simple_temp-0.0.2.dist-info/entry_points.txt
yoshi_simple_temp-0.0.2.dist-info/top_level.txt
yoshi_simple_temp-0.0.2.dist-info/RECORD
