Metadata-Version: 2.1
Name: yoshi-simple-temp
Version: 0.0.2
Summary: YOUR DESCRIPTION HERE
Home-page: https://github.com/Yoshibansal/py-package-starter-temp
Author: Yoshi Bansal
Author-email: <bansalyoshi@gmail.com>
License: MIT
Keywords: python,simple
Platform: UNKNOWN
Classifier: Development Status :: 1 - Planning
Classifier: Intended Audience :: Developers
Classifier: Programming Language :: Python :: 3
Classifier: Operating System :: Unix
Classifier: Operating System :: MacOS :: MacOS X
Classifier: Operating System :: Microsoft :: Windows
License-File: LICENSE
Requires-Dist: numpy
Requires-Dist: pandas
Requires-Dist: pyfiglet
